supertone/__init__.py
supertone/_version.py
supertone/basesdk.py
supertone/custom_voices.py
supertone/httpclient.py
supertone/py.typed
supertone/sdk.py
supertone/sdkconfiguration.py
supertone/text_to_speech.py
supertone/usage.py
supertone/voices.py
supertone/_hooks/__init__.py
supertone/_hooks/sdkhooks.py
supertone/_hooks/types.py
supertone/custom_utils/__init__.py
supertone/custom_utils/audio_utils.py
supertone/custom_utils/constants.py
supertone/custom_utils/logger_utils.py
supertone/custom_utils/phoneme_utils.py
supertone/custom_utils/pronunciation_utils.py
supertone/custom_utils/text_utils.py
supertone/errors/__init__.py
supertone/errors/badrequesterrorresponse.py
supertone/errors/forbiddenerrorresponse.py
supertone/errors/internalservererrorresponse.py
supertone/errors/no_response_error.py
supertone/errors/notfounderrorresponse.py
supertone/errors/payloadtoolargeerrorresponse.py
supertone/errors/paymentrequirederrorresponse.py
supertone/errors/requesttimeouterrorresponse.py
supertone/errors/responsevalidationerror.py
supertone/errors/supertonedefaulterror.py
supertone/errors/supertoneerror.py
supertone/errors/toomanyrequestserrorresponse.py
supertone/errors/unauthorizederrorresponse.py
supertone/errors/unsupportedmediatypeerrorresponse.py
supertone/models/__init__.py
supertone/models/apiconverttexttospeechusingcharacterrequest.py
supertone/models/apisampledata.py
supertone/models/converttexttospeechparameters.py
supertone/models/create_cloned_voiceop.py
supertone/models/create_speechop.py
supertone/models/createcustomvoiceresponse.py
supertone/models/delete_custom_voiceop.py
supertone/models/edit_custom_voiceop.py
supertone/models/forbiddenerrorresponse.py
supertone/models/get_custom_voiceop.py
supertone/models/get_usageop.py
supertone/models/get_voice_usageop.py
supertone/models/get_voiceop.py
supertone/models/getapicharacterlistresponse.py
supertone/models/getapicharacterresponsedata.py
supertone/models/getcharacterbyidresponse.py
supertone-0.1.5.dist-info/licenses/LICENSE
supertone-0.1.5.dist-info/METADATA
supertone-0.1.5.dist-info/WHEEL
supertone-0.1.5.dist-info/top_level.txt
supertone-0.1.5.dist-info/RECORD
