Metadata-Version: 2.4
Name: supertone
Version: 0.1.5
Summary: Python Client SDK for Supertone API Generated by Supertone.
Author: Supertone, Pillip Youn
Requires-Python: >=3.12
License-File: LICENSE
Requires-Dist: httpcore>=1.0.9
Requires-Dist: httpx>=0.28.1
Requires-Dist: numpy>=2.4.1
Requires-Dist: pydantic>=2.11.2
Requires-Dist: python-dotenv>=1.2.1
Requires-Dist: sounddevice>=0.5.3
Dynamic: license-file
